django_core_micha/__init__.py
django_core_micha/api_urls.py
django_core_micha/auth/__init__.py
django_core_micha/auth/adapters.py
django_core_micha/auth/apps.py
django_core_micha/auth/exception_handler.py
django_core_micha/auth/middleware.py
django_core_micha/auth/models.py
django_core_micha/auth/permissions.py
django_core_micha/auth/recovery.py
django_core_micha/auth/roles.py
django_core_micha/auth/security.py
django_core_micha/auth/serializers.py
django_core_micha/auth/services.py
django_core_micha/auth/signals.py
django_core_micha/auth/views.py
django_core_micha/auth/migrations/0001_initial.py
django_core_micha/auth/migrations/0002_recoveryrequest_support_note.py
django_core_micha/auth/migrations/__init__.py
django_core_micha/emails/__init__.py
django_core_micha/emails/email_texts.py
django_core_micha/invitations/__init__.py
django_core_micha/invitations/access_codes.py
django_core_micha/invitations/apps.py
django_core_micha/invitations/conf.py
django_core_micha/invitations/emails.py
django_core_micha/invitations/mixins.py
django_core_micha/invitations/models.py
django_core_micha/invitations/serializers.py
django_core_micha/invitations/urls.py
django_core_micha/invitations/views.py
django_core_micha/invitations/migrations/0001_initial.py
django_core_micha/invitations/migrations/__init__.py
django_core_micha/scripts/__init__.py
django_core_micha/scripts/generate_env.py
django_core_micha/scripts/sync_secrets.py
django_core_micha/settings/__init__.py
django_core_micha/settings/dev_settings.py
django_core_micha/settings/settings_base.py
django_core_micha-2.2.22.dist-info/METADATA
django_core_micha-2.2.22.dist-info/WHEEL
django_core_micha-2.2.22.dist-info/entry_points.txt
django_core_micha-2.2.22.dist-info/top_level.txt
django_core_micha-2.2.22.dist-info/RECORD
