Metadata-Version: 2.4
Name: django-core-micha
Version: 2.2.22
Summary: Core utilities and settings for Django Apps
Author-email: Micha Bigler <micha.bigler2@gmail.com>
Project-URL: Homepage, https://github.com/MichaBigler/webapp-management
Requires-Python: >=3.10
Requires-Dist: Django>=4.0
Requires-Dist: PyYAML
Requires-Dist: psycopg2-binary
